hotkeynet/__init__.py
hotkeynet/_version.py
hotkeynet/api.py
hotkeynet/canned.py
hotkeynet/keyname.py
hotkeynet/maker.py
hotkeynet/script.py
hotkeynet/utils.py
hotkeynet/__pycache__/__init__.cpython-310.pyc
hotkeynet/__pycache__/_version.cpython-310.pyc
hotkeynet/__pycache__/api.cpython-310.pyc
hotkeynet/__pycache__/canned.cpython-310.pyc
hotkeynet/__pycache__/keyname.cpython-310.pyc
hotkeynet/__pycache__/maker.cpython-310.pyc
hotkeynet/__pycache__/script.cpython-310.pyc
hotkeynet/__pycache__/utils.cpython-310.pyc
hotkeynet/docs/__init__.py
hotkeynet/docs/__pycache__/__init__.cpython-310.pyc
hotkeynet/tests/__init__.py
hotkeynet/tests/helper.py
hotkeynet/tests/paths.py
hotkeynet/tests/__pycache__/__init__.cpython-310.pyc
hotkeynet/tests/__pycache__/helper.cpython-310.pyc
hotkeynet/tests/__pycache__/paths.cpython-310.pyc
hotkeynet/tpl/Block.tpl
hotkeynet/tpl/Script.tpl
hotkeynet/tpl/__init__.py
hotkeynet/tpl/__pycache__/__init__.cpython-310.pyc
hotkeynet/vendor/__init__.py
hotkeynet/vendor/better_enum.py
hotkeynet/vendor/pytest_cov_helper.py
hotkeynet/vendor/__pycache__/__init__.cpython-310.pyc
hotkeynet/vendor/__pycache__/better_enum.cpython-310.pyc
hotkeynet/vendor/__pycache__/pytest_cov_helper.cpython-310.pyc
hotkeynet-0.1.7.dist-info/AUTHORS.rst
hotkeynet-0.1.7.dist-info/LICENSE.txt
hotkeynet-0.1.7.dist-info/METADATA
hotkeynet-0.1.7.dist-info/WHEEL
hotkeynet-0.1.7.dist-info/top_level.txt
hotkeynet-0.1.7.dist-info/RECORD
